epicstore_api/__init__.py
epicstore_api/api.py
epicstore_api/exc.py
epicstore_api/queries.py
epicstore_api/models/__init__.py
epicstore_api/models/categories.py
epicstore_api/models/collection_types.py
epicstore_api/models/product_types.py
epicstore_api_additions-0.2.4.dist-info/licenses/LICENSE
epicstore_api_additions-0.2.4.dist-info/METADATA
epicstore_api_additions-0.2.4.dist-info/WHEEL
epicstore_api_additions-0.2.4.dist-info/top_level.txt
epicstore_api_additions-0.2.4.dist-info/RECORD
